utrainer/__init__.py
utrainer/attack_train_utils.py
utrainer/base.py
utrainer/logger.py
utrainer/metric.py
utrainer/optimizer_utils.py
u_trainer-1.0.11.dist-info/LICENSE
u_trainer-1.0.11.dist-info/METADATA
u_trainer-1.0.11.dist-info/WHEEL
u_trainer-1.0.11.dist-info/top_level.txt
u_trainer-1.0.11.dist-info/RECORD
