Metadata-Version: 2.1
Name: u-trainer
Version: 1.0.11
Summary: trainer
Home-page: https://github.com/geasyheart/u-trainer
Author: yuzhang
Author-email: geasyheart@163.com
License: MIT
Platform: UNKNOWN
